SpiralMap/__init__.py
SpiralMap/models_.py
SpiralMap/movie_.gif
SpiralMap/mytools.py
SpiralMap/test.py
SpiralMap/version.py
SpiralMap/datafiles/flim.pkl
SpiralMap/datafiles/flim_all.pkl
SpiralMap/datafiles/spiral.bib
SpiralMap/datafiles/Drimmel2024_cepheids/ArmAttributes_dyoungW1_bw025.pkl
SpiralMap/datafiles/Drimmel_NIR/Drimmel2armspiral.fits
SpiralMap/datafiles/Drimmel_NIR/Readme_spiral_m2_147.txt
SpiralMap/datafiles/Drimmel_NIR/spiral_m2_147.dat
SpiralMap/datafiles/Drimmel_NIR/phase_shifted/Arm1_X_hel.npy
SpiralMap/datafiles/Drimmel_NIR/phase_shifted/Arm1_Y_hel.npy
SpiralMap/datafiles/Drimmel_NIR/phase_shifted/Arm2_X_hel.npy
SpiralMap/datafiles/Drimmel_NIR/phase_shifted/Arm2_Y_hel.npy
SpiralMap/datafiles/Drimmel_NIR/phase_shifted/Arm3_X_hel.npy
SpiralMap/datafiles/Drimmel_NIR/phase_shifted/Arm3_Y_hel.npy
SpiralMap/datafiles/Drimmel_NIR/phase_shifted/Arm4_X_hel.npy
SpiralMap/datafiles/Drimmel_NIR/phase_shifted/Arm4_Y_hel.npy
SpiralMap/datafiles/GaiaPVP_cont_2022/GaiaPVP_cont_2022_pproj_contours.pkl
SpiralMap/datafiles/GaiaPVP_cont_2022/over_dens_grid_threshold_0_003_dens.npy
SpiralMap/datafiles/GaiaPVP_cont_2022/xvalues_dens.npy
SpiralMap/datafiles/GaiaPVP_cont_2022/yvalues_dens.npy
SpiralMap/datafiles/Poggio_cont_2021/Poggio_cont_2021_pproj_contours.pkl
SpiralMap/datafiles/Poggio_cont_2021/overdens_grid_locscale03.npy
SpiralMap/datafiles/Poggio_cont_2021/xvalues.npy
SpiralMap/datafiles/Poggio_cont_2021/yvalues.npy
SpiralMap/figdir_primer/map_0png.png
SpiralMap/figdir_primer/map_1png.png
SpiralMap/figdir_primer/map_2png.png
SpiralMap/figdir_primer/map_3png.png
SpiralMap/figdir_primer/map_4png.png
SpiralMap/figdir_primer/map_5png.png
SpiralMap/figdir_primer/map_8png.png
spiralmap-0.0.21.dist-info/METADATA
spiralmap-0.0.21.dist-info/WHEEL
spiralmap-0.0.21.dist-info/licenses/LICENSE.md
spiralmap-0.0.21.dist-info/RECORD
