Metadata-Version: 2.4
Name: SpiralMap
Version: 0.0.21
Summary: Python Library of Milky Way's Spiral Arms
Project-URL: Homepage, https://github.com/Abhaypru/SpiralMap
Project-URL: Issues, https://github.com/Abhaypru/SpiralMap/issues
Author-email: Prusty & Khanna <shourya.khanna@inaf.it>
License-Expression: MIT
License-File: LICENSE.md
Classifier: Operating System :: OS Independent
Classifier: Programming Language :: Python :: 3
Requires-Python: >=3.9
Provides-Extra: docs
Requires-Dist: sphinx; extra == 'docs'
Requires-Dist: sphinx-rtd-theme; extra == 'docs'
Requires-Dist: sphinxcontrib-bibtex; extra == 'docs'
